moss_decoder-1.0.0.dist-info/METADATA
moss_decoder-1.0.0.dist-info/WHEEL
moss_decoder/__init__.py
moss_decoder/__init__.pyi
moss_decoder/py.typed
moss_decoder/moss_decoder.cpython-311-i386-linux-gnu.so
moss_decoder-1.0.0.dist-info/RECORD
