Metadata-Version: 2.1
Name: moss_decoder
Version: 1.0.0
Classifier: Programming Language :: Rust
Classifier: Programming Language :: Python :: Implementation :: CPython
Classifier: Programming Language :: Python :: Implementation :: PyPy
Summary: Python package implemented in Rust to decode MOSS readout data
Author: Marc Beck König
Author-email: marc.beck.konig@cern.ch
Maintainer-email: Marc Beck König <marc.beck.konig@cern.ch>
License: MIT OR Apache-2.0
Requires-Python: >=3.7
